LICENSE.txt
MANIFEST.in
README.rst
setup.cfg
setup.py
pycicu/__init__.py
pycicu/models.py
pycicu/schemas.py
pycicu/views.py
pycicu/widget.py
pycicu.egg-info/PKG-INFO
pycicu.egg-info/SOURCES.txt
pycicu.egg-info/dependency_links.txt
pycicu.egg-info/entry_points.txt
pycicu.egg-info/not-zip-safe
pycicu.egg-info/requires.txt
pycicu.egg-info/top_level.txt
pycicu/scripts/__init__.py
pycicu/scripts/initializedb.py
pycicu/static/css/Jcrop.gif
pycicu/static/css/jquery.Jcrop.css
pycicu/static/css/jquery.Jcrop.min.css
pycicu/static/css/pycicu-widget.css
pycicu/static/js/jquery.Jcrop.js
pycicu/static/js/jquery.Jcrop.min.js
pycicu/static/js/jquery.iframe-transport.js
pycicu/static/js/pycicu-widget.js
pycicu/templates/croped_photo_upload.pt
pycicu/templates/teste.pt