Metadata-Version: 1.1
Name: pycicu
Version: 0.1.5.6
Summary: PyClean Image Crop Uploader (pycicu) provides AJAX file upload and image CROP functionalitiesusing Pyramid. It uses Modal from twitter-bootstrap. This is a fork of clean-image-crop-uploader.
Home-page: UNKNOWN
Author: kalkehcoisa
Author-email: kalkehcoisa@gmail.com
License: UNKNOWN
Keywords: web pylons pyramid upload image crop
Platform: UNKNOWN
Classifier: Development Status :: 3 - Alpha
Classifier: Environment :: Web Environment
Classifier: Framework :: Pyramid
Classifier: Intended Audience :: Developers
Classifier: Operating System :: OS Independent
Classifier: Programming Language :: Python
Classifier: Topic :: Software Development :: Libraries :: Python Modules
